Metadata-Version: 2.1
Name: adapter-transformers
Version: 3.2.1.post0
Summary: A friendly fork of HuggingFace's Transformers, adding Adapters to PyTorch language models
Home-page: https://github.com/adapter-hub/adapter-transformers
Author: Jonas Pfeiffer, Andreas Rücklé, Clifton Poth, Hannah Sterz, Leon Engländer, based on work by the HuggingFace team and community
Author-email: pfeiffer@ukp.tu-darmstadt.de
License: Apache
Keywords: NLP deep learning transformer pytorch BERT adapters
Platform: UNKNOWN
Classifier: Development Status :: 7 - Inactive
Classifier: Intended Audience :: Developers
Classifier: Intended Audience :: Education
Classifier: Intended Audience :: Science/Research
Classifier: License :: OSI Approved :: Apache Software License
Classifier: Operating System :: OS Independent
Classifier: Programming Language :: Python :: 3
Classifier: Programming Language :: Python :: 3.8
Classifier: Programming Language :: Python :: 3.9
Classifier: Programming Language :: Python :: 3.10
Classifier: Topic :: Scientific/Engineering :: Artificial Intelligence
Requires-Python: >=3.8.0
License-File: LICENSE
Requires-Dist: filelock
Requires-Dist: huggingface-hub (<0.14.0,>=0.11.0)
Requires-Dist: numpy (>=1.17)
Requires-Dist: packaging (>=20.0)
Requires-Dist: pyyaml (>=5.1)
Requires-Dist: regex (!=2019.12.17)
Requires-Dist: requests
Requires-Dist: tokenizers (!=0.11.3,<0.14,>=0.11.1)
Requires-Dist: tqdm (>=4.27)
Requires-Dist: importlib-metadata ; python_version < "3.8"
Provides-Extra: accelerate
Requires-Dist: accelerate (>=0.10.0) ; extra == 'accelerate'
Provides-Extra: all
Requires-Dist: tensorflow (<2.12,>=2.4) ; extra == 'all'
Requires-Dist: onnxconverter-common ; extra == 'all'
Requires-Dist: tf2onnx ; extra == 'all'
Requires-Dist: tensorflow-text ; extra == 'all'
Requires-Dist: keras-nlp (>=0.3.1) ; extra == 'all'
Requires-Dist: torch (>=1.12.1) ; extra == 'all'
Requires-Dist: sentencepiece (!=0.1.92,>=0.1.91) ; extra == 'all'
Requires-Dist: protobuf (<=3.20.2) ; extra == 'all'
Requires-Dist: tokenizers (!=0.11.3,<0.14,>=0.11.1) ; extra == 'all'
Requires-Dist: torchaudio ; extra == 'all'
Requires-Dist: librosa ; extra == 'all'
Requires-Dist: pyctcdecode (>=0.4.0) ; extra == 'all'
Requires-Dist: phonemizer ; extra == 'all'
Requires-Dist: kenlm ; extra == 'all'
Requires-Dist: Pillow ; extra == 'all'
Requires-Dist: optuna ; extra == 'all'
Requires-Dist: ray[tune] ; extra == 'all'
Requires-Dist: sigopt ; extra == 'all'
Requires-Dist: timm ; extra == 'all'
Requires-Dist: codecarbon (==1.2.0) ; extra == 'all'
Requires-Dist: accelerate (>=0.10.0) ; extra == 'all'
Requires-Dist: decord (==0.6.0) ; extra == 'all'
Provides-Extra: audio
Requires-Dist: librosa ; extra == 'audio'
Requires-Dist: pyctcdecode (>=0.4.0) ; extra == 'audio'
Requires-Dist: phonemizer ; extra == 'audio'
Requires-Dist: kenlm ; extra == 'audio'
Provides-Extra: codecarbon
Requires-Dist: codecarbon (==1.2.0) ; extra == 'codecarbon'
Provides-Extra: deepspeed
Requires-Dist: deepspeed (>=0.6.5) ; extra == 'deepspeed'
Requires-Dist: accelerate (>=0.10.0) ; extra == 'deepspeed'
Provides-Extra: deepspeed-testing
Requires-Dist: deepspeed (>=0.6.5) ; extra == 'deepspeed-testing'
Requires-Dist: accelerate (>=0.10.0) ; extra == 'deepspeed-testing'
Requires-Dist: pytest ; extra == 'deepspeed-testing'
Requires-Dist: pytest-xdist ; extra == 'deepspeed-testing'
Requires-Dist: timeout-decorator ; extra == 'deepspeed-testing'
Requires-Dist: parameterized ; extra == 'deepspeed-testing'
Requires-Dist: psutil ; extra == 'deepspeed-testing'
Requires-Dist: datasets (!=2.5.0) ; extra == 'deepspeed-testing'
Requires-Dist: dill (<0.3.5) ; extra == 'deepspeed-testing'
Requires-Dist: evaluate (>=0.2.0) ; extra == 'deepspeed-testing'
Requires-Dist: pytest-timeout ; extra == 'deepspeed-testing'
Requires-Dist: black (==22.3) ; extra == 'deepspeed-testing'
Requires-Dist: sacrebleu (<2.0.0,>=1.4.12) ; extra == 'deepspeed-testing'
Requires-Dist: rouge-score (!=0.0.7,!=0.0.8,!=0.1,!=0.1.1) ; extra == 'deepspeed-testing'
Requires-Dist: nltk ; extra == 'deepspeed-testing'
Requires-Dist: GitPython (<3.1.19) ; extra == 'deepspeed-testing'
Requires-Dist: hf-doc-builder (>=0.3.0) ; extra == 'deepspeed-testing'
Requires-Dist: protobuf (<=3.20.2) ; extra == 'deepspeed-testing'
Requires-Dist: sacremoses ; extra == 'deepspeed-testing'
Requires-Dist: rjieba ; extra == 'deepspeed-testing'
Requires-Dist: safetensors (>=0.2.1) ; extra == 'deepspeed-testing'
Requires-Dist: beautifulsoup4 ; extra == 'deepspeed-testing'
Requires-Dist: cookiecutter (==1.7.3) ; extra == 'deepspeed-testing'
Requires-Dist: optuna ; extra == 'deepspeed-testing'
Requires-Dist: sentencepiece (!=0.1.92,>=0.1.91) ; extra == 'deepspeed-testing'
Provides-Extra: dev
Requires-Dist: tensorflow (<2.12,>=2.4) ; extra == 'dev'
Requires-Dist: onnxconverter-common ; extra == 'dev'
Requires-Dist: tf2onnx ; extra == 'dev'
Requires-Dist: tensorflow-text ; extra == 'dev'
Requires-Dist: keras-nlp (>=0.3.1) ; extra == 'dev'
Requires-Dist: torch (>=1.12.1) ; extra == 'dev'
Requires-Dist: sentencepiece (!=0.1.92,>=0.1.91) ; extra == 'dev'
Requires-Dist: protobuf (<=3.20.2) ; extra == 'dev'
Requires-Dist: tokenizers (!=0.11.3,<0.14,>=0.11.1) ; extra == 'dev'
Requires-Dist: torchaudio ; extra == 'dev'
Requires-Dist: librosa ; extra == 'dev'
Requires-Dist: pyctcdecode (>=0.4.0) ; extra == 'dev'
Requires-Dist: phonemizer ; extra == 'dev'
Requires-Dist: kenlm ; extra == 'dev'
Requires-Dist: Pillow ; extra == 'dev'
Requires-Dist: optuna ; extra == 'dev'
Requires-Dist: ray[tune] ; extra == 'dev'
Requires-Dist: sigopt ; extra == 'dev'
Requires-Dist: timm ; extra == 'dev'
Requires-Dist: codecarbon (==1.2.0) ; extra == 'dev'
Requires-Dist: accelerate (>=0.10.0) ; extra == 'dev'
Requires-Dist: decord (==0.6.0) ; extra == 'dev'
Requires-Dist: pytest ; extra == 'dev'
Requires-Dist: pytest-xdist ; extra == 'dev'
Requires-Dist: timeout-decorator ; extra == 'dev'
Requires-Dist: parameterized ; extra == 'dev'
Requires-Dist: psutil ; extra == 'dev'
Requires-Dist: datasets (!=2.5.0) ; extra == 'dev'
Requires-Dist: dill (<0.3.5) ; extra == 'dev'
Requires-Dist: evaluate (>=0.2.0) ; extra == 'dev'
Requires-Dist: pytest-timeout ; extra == 'dev'
Requires-Dist: black (==22.3) ; extra == 'dev'
Requires-Dist: sacrebleu (<2.0.0,>=1.4.12) ; extra == 'dev'
Requires-Dist: rouge-score (!=0.0.7,!=0.0.8,!=0.1,!=0.1.1) ; extra == 'dev'
Requires-Dist: nltk ; extra == 'dev'
Requires-Dist: GitPython (<3.1.19) ; extra == 'dev'
Requires-Dist: hf-doc-builder (>=0.3.0) ; extra == 'dev'
Requires-Dist: sacremoses ; extra == 'dev'
Requires-Dist: rjieba ; extra == 'dev'
Requires-Dist: safetensors (>=0.2.1) ; extra == 'dev'
Requires-Dist: beautifulsoup4 ; extra == 'dev'
Requires-Dist: cookiecutter (==1.7.3) ; extra == 'dev'
Requires-Dist: isort (>=5.5.4) ; extra == 'dev'
Requires-Dist: flake8 (<6.0.0,>=3.8.3) ; extra == 'dev'
Requires-Dist: fugashi (>=1.0) ; extra == 'dev'
Requires-Dist: ipadic (<2.0,>=1.0.0) ; extra == 'dev'
Requires-Dist: unidic-lite (>=1.0.7) ; extra == 'dev'
Requires-Dist: unidic (>=1.0.2) ; extra == 'dev'
Requires-Dist: sudachipy (>=0.6.6) ; extra == 'dev'
Requires-Dist: sudachidict-core (>=20220729) ; extra == 'dev'
Requires-Dist: rhoknp (>=1.1.0) ; extra == 'dev'
Requires-Dist: docutils (==0.16.0) ; extra == 'dev'
Requires-Dist: myst-parser ; extra == 'dev'
Requires-Dist: sphinx (==3.2.1) ; extra == 'dev'
Requires-Dist: sphinx-markdown-tables ; extra == 'dev'
Requires-Dist: sphinx-rtd-theme (==0.4.3) ; extra == 'dev'
Requires-Dist: sphinx-copybutton ; extra == 'dev'
Requires-Dist: sphinxext-opengraph (==0.4.1) ; extra == 'dev'
Requires-Dist: sphinx-intl ; extra == 'dev'
Requires-Dist: sphinx-multiversion ; extra == 'dev'
Requires-Dist: scikit-learn ; extra == 'dev'
Provides-Extra: dev-tensorflow
Requires-Dist: pytest ; extra == 'dev-tensorflow'
Requires-Dist: pytest-xdist ; extra == 'dev-tensorflow'
Requires-Dist: timeout-decorator ; extra == 'dev-tensorflow'
Requires-Dist: parameterized ; extra == 'dev-tensorflow'
Requires-Dist: psutil ; extra == 'dev-tensorflow'
Requires-Dist: datasets (!=2.5.0) ; extra == 'dev-tensorflow'
Requires-Dist: dill (<0.3.5) ; extra == 'dev-tensorflow'
Requires-Dist: evaluate (>=0.2.0) ; extra == 'dev-tensorflow'
Requires-Dist: pytest-timeout ; extra == 'dev-tensorflow'
Requires-Dist: black (==22.3) ; extra == 'dev-tensorflow'
Requires-Dist: sacrebleu (<2.0.0,>=1.4.12) ; extra == 'dev-tensorflow'
Requires-Dist: rouge-score (!=0.0.7,!=0.0.8,!=0.1,!=0.1.1) ; extra == 'dev-tensorflow'
Requires-Dist: nltk ; extra == 'dev-tensorflow'
Requires-Dist: GitPython (<3.1.19) ; extra == 'dev-tensorflow'
Requires-Dist: hf-doc-builder (>=0.3.0) ; extra == 'dev-tensorflow'
Requires-Dist: protobuf (<=3.20.2) ; extra == 'dev-tensorflow'
Requires-Dist: sacremoses ; extra == 'dev-tensorflow'
Requires-Dist: rjieba ; extra == 'dev-tensorflow'
Requires-Dist: safetensors (>=0.2.1) ; extra == 'dev-tensorflow'
Requires-Dist: beautifulsoup4 ; extra == 'dev-tensorflow'
Requires-Dist: cookiecutter (==1.7.3) ; extra == 'dev-tensorflow'
Requires-Dist: tensorflow (<2.12,>=2.4) ; extra == 'dev-tensorflow'
Requires-Dist: onnxconverter-common ; extra == 'dev-tensorflow'
Requires-Dist: tf2onnx ; extra == 'dev-tensorflow'
Requires-Dist: tensorflow-text ; extra == 'dev-tensorflow'
Requires-Dist: keras-nlp (>=0.3.1) ; extra == 'dev-tensorflow'
Requires-Dist: sentencepiece (!=0.1.92,>=0.1.91) ; extra == 'dev-tensorflow'
Requires-Dist: tokenizers (!=0.11.3,<0.14,>=0.11.1) ; extra == 'dev-tensorflow'
Requires-Dist: Pillow ; extra == 'dev-tensorflow'
Requires-Dist: isort (>=5.5.4) ; extra == 'dev-tensorflow'
Requires-Dist: flake8 (<6.0.0,>=3.8.3) ; extra == 'dev-tensorflow'
Requires-Dist: docutils (==0.16.0) ; extra == 'dev-tensorflow'
Requires-Dist: myst-parser ; extra == 'dev-tensorflow'
Requires-Dist: sphinx (==3.2.1) ; extra == 'dev-tensorflow'
Requires-Dist: sphinx-markdown-tables ; extra == 'dev-tensorflow'
Requires-Dist: sphinx-rtd-theme (==0.4.3) ; extra == 'dev-tensorflow'
Requires-Dist: sphinx-copybutton ; extra == 'dev-tensorflow'
Requires-Dist: sphinxext-opengraph (==0.4.1) ; extra == 'dev-tensorflow'
Requires-Dist: sphinx-intl ; extra == 'dev-tensorflow'
Requires-Dist: sphinx-multiversion ; extra == 'dev-tensorflow'
Requires-Dist: scikit-learn ; extra == 'dev-tensorflow'
Requires-Dist: onnxruntime (>=1.4.0) ; extra == 'dev-tensorflow'
Requires-Dist: onnxruntime-tools (>=1.4.2) ; extra == 'dev-tensorflow'
Requires-Dist: librosa ; extra == 'dev-tensorflow'
Requires-Dist: pyctcdecode (>=0.4.0) ; extra == 'dev-tensorflow'
Requires-Dist: phonemizer ; extra == 'dev-tensorflow'
Requires-Dist: kenlm ; extra == 'dev-tensorflow'
Provides-Extra: dev-torch
Requires-Dist: pytest ; extra == 'dev-torch'
Requires-Dist: pytest-xdist ; extra == 'dev-torch'
Requires-Dist: timeout-decorator ; extra == 'dev-torch'
Requires-Dist: parameterized ; extra == 'dev-torch'
Requires-Dist: psutil ; extra == 'dev-torch'
Requires-Dist: datasets (!=2.5.0) ; extra == 'dev-torch'
Requires-Dist: dill (<0.3.5) ; extra == 'dev-torch'
Requires-Dist: evaluate (>=0.2.0) ; extra == 'dev-torch'
Requires-Dist: pytest-timeout ; extra == 'dev-torch'
Requires-Dist: black (==22.3) ; extra == 'dev-torch'
Requires-Dist: sacrebleu (<2.0.0,>=1.4.12) ; extra == 'dev-torch'
Requires-Dist: rouge-score (!=0.0.7,!=0.0.8,!=0.1,!=0.1.1) ; extra == 'dev-torch'
Requires-Dist: nltk ; extra == 'dev-torch'
Requires-Dist: GitPython (<3.1.19) ; extra == 'dev-torch'
Requires-Dist: hf-doc-builder (>=0.3.0) ; extra == 'dev-torch'
Requires-Dist: protobuf (<=3.20.2) ; extra == 'dev-torch'
Requires-Dist: sacremoses ; extra == 'dev-torch'
Requires-Dist: rjieba ; extra == 'dev-torch'
Requires-Dist: safetensors (>=0.2.1) ; extra == 'dev-torch'
Requires-Dist: beautifulsoup4 ; extra == 'dev-torch'
Requires-Dist: cookiecutter (==1.7.3) ; extra == 'dev-torch'
Requires-Dist: torch (>=1.12.1) ; extra == 'dev-torch'
Requires-Dist: sentencepiece (!=0.1.92,>=0.1.91) ; extra == 'dev-torch'
Requires-Dist: tokenizers (!=0.11.3,<0.14,>=0.11.1) ; extra == 'dev-torch'
Requires-Dist: torchaudio ; extra == 'dev-torch'
Requires-Dist: librosa ; extra == 'dev-torch'
Requires-Dist: pyctcdecode (>=0.4.0) ; extra == 'dev-torch'
Requires-Dist: phonemizer ; extra == 'dev-torch'
Requires-Dist: kenlm ; extra == 'dev-torch'
Requires-Dist: Pillow ; extra == 'dev-torch'
Requires-Dist: optuna ; extra == 'dev-torch'
Requires-Dist: ray[tune] ; extra == 'dev-torch'
Requires-Dist: sigopt ; extra == 'dev-torch'
Requires-Dist: timm ; extra == 'dev-torch'
Requires-Dist: codecarbon (==1.2.0) ; extra == 'dev-torch'
Requires-Dist: isort (>=5.5.4) ; extra == 'dev-torch'
Requires-Dist: flake8 (<6.0.0,>=3.8.3) ; extra == 'dev-torch'
Requires-Dist: fugashi (>=1.0) ; extra == 'dev-torch'
Requires-Dist: ipadic (<2.0,>=1.0.0) ; extra == 'dev-torch'
Requires-Dist: unidic-lite (>=1.0.7) ; extra == 'dev-torch'
Requires-Dist: unidic (>=1.0.2) ; extra == 'dev-torch'
Requires-Dist: sudachipy (>=0.6.6) ; extra == 'dev-torch'
Requires-Dist: sudachidict-core (>=20220729) ; extra == 'dev-torch'
Requires-Dist: rhoknp (>=1.1.0) ; extra == 'dev-torch'
Requires-Dist: docutils (==0.16.0) ; extra == 'dev-torch'
Requires-Dist: myst-parser ; extra == 'dev-torch'
Requires-Dist: sphinx (==3.2.1) ; extra == 'dev-torch'
Requires-Dist: sphinx-markdown-tables ; extra == 'dev-torch'
Requires-Dist: sphinx-rtd-theme (==0.4.3) ; extra == 'dev-torch'
Requires-Dist: sphinx-copybutton ; extra == 'dev-torch'
Requires-Dist: sphinxext-opengraph (==0.4.1) ; extra == 'dev-torch'
Requires-Dist: sphinx-intl ; extra == 'dev-torch'
Requires-Dist: sphinx-multiversion ; extra == 'dev-torch'
Requires-Dist: scikit-learn ; extra == 'dev-torch'
Requires-Dist: onnxruntime (>=1.4.0) ; extra == 'dev-torch'
Requires-Dist: onnxruntime-tools (>=1.4.2) ; extra == 'dev-torch'
Provides-Extra: docs
Requires-Dist: tensorflow (<2.12,>=2.4) ; extra == 'docs'
Requires-Dist: onnxconverter-common ; extra == 'docs'
Requires-Dist: tf2onnx ; extra == 'docs'
Requires-Dist: tensorflow-text ; extra == 'docs'
Requires-Dist: keras-nlp (>=0.3.1) ; extra == 'docs'
Requires-Dist: torch (>=1.12.1) ; extra == 'docs'
Requires-Dist: sentencepiece (!=0.1.92,>=0.1.91) ; extra == 'docs'
Requires-Dist: protobuf (<=3.20.2) ; extra == 'docs'
Requires-Dist: tokenizers (!=0.11.3,<0.14,>=0.11.1) ; extra == 'docs'
Requires-Dist: torchaudio ; extra == 'docs'
Requires-Dist: librosa ; extra == 'docs'
Requires-Dist: pyctcdecode (>=0.4.0) ; extra == 'docs'
Requires-Dist: phonemizer ; extra == 'docs'
Requires-Dist: kenlm ; extra == 'docs'
Requires-Dist: Pillow ; extra == 'docs'
Requires-Dist: optuna ; extra == 'docs'
Requires-Dist: ray[tune] ; extra == 'docs'
Requires-Dist: sigopt ; extra == 'docs'
Requires-Dist: timm ; extra == 'docs'
Requires-Dist: codecarbon (==1.2.0) ; extra == 'docs'
Requires-Dist: accelerate (>=0.10.0) ; extra == 'docs'
Requires-Dist: decord (==0.6.0) ; extra == 'docs'
Requires-Dist: docutils (==0.16.0) ; extra == 'docs'
Requires-Dist: myst-parser ; extra == 'docs'
Requires-Dist: sphinx (==3.2.1) ; extra == 'docs'
Requires-Dist: sphinx-markdown-tables ; extra == 'docs'
Requires-Dist: sphinx-rtd-theme (==0.4.3) ; extra == 'docs'
Requires-Dist: sphinx-copybutton ; extra == 'docs'
Requires-Dist: sphinxext-opengraph (==0.4.1) ; extra == 'docs'
Requires-Dist: sphinx-intl ; extra == 'docs'
Requires-Dist: sphinx-multiversion ; extra == 'docs'
Provides-Extra: docs_specific
Requires-Dist: docutils (==0.16.0) ; extra == 'docs_specific'
Requires-Dist: myst-parser ; extra == 'docs_specific'
Requires-Dist: sphinx (==3.2.1) ; extra == 'docs_specific'
Requires-Dist: sphinx-markdown-tables ; extra == 'docs_specific'
Requires-Dist: sphinx-rtd-theme (==0.4.3) ; extra == 'docs_specific'
Requires-Dist: sphinx-copybutton ; extra == 'docs_specific'
Requires-Dist: sphinxext-opengraph (==0.4.1) ; extra == 'docs_specific'
Requires-Dist: sphinx-intl ; extra == 'docs_specific'
Requires-Dist: sphinx-multiversion ; extra == 'docs_specific'
Provides-Extra: fairscale
Requires-Dist: fairscale (>0.3) ; extra == 'fairscale'
Provides-Extra: flax
Provides-Extra: flax-speech
Requires-Dist: librosa ; extra == 'flax-speech'
Requires-Dist: pyctcdecode (>=0.4.0) ; extra == 'flax-speech'
Requires-Dist: phonemizer ; extra == 'flax-speech'
Requires-Dist: kenlm ; extra == 'flax-speech'
Provides-Extra: ftfy
Requires-Dist: ftfy ; extra == 'ftfy'
Provides-Extra: integrations
Requires-Dist: optuna ; extra == 'integrations'
Requires-Dist: ray[tune] ; extra == 'integrations'
Requires-Dist: sigopt ; extra == 'integrations'
Provides-Extra: ja
Requires-Dist: fugashi (>=1.0) ; extra == 'ja'
Requires-Dist: ipadic (<2.0,>=1.0.0) ; extra == 'ja'
Requires-Dist: unidic-lite (>=1.0.7) ; extra == 'ja'
Requires-Dist: unidic (>=1.0.2) ; extra == 'ja'
Requires-Dist: sudachipy (>=0.6.6) ; extra == 'ja'
Requires-Dist: sudachidict-core (>=20220729) ; extra == 'ja'
Requires-Dist: rhoknp (>=1.1.0) ; extra == 'ja'
Provides-Extra: modelcreation
Requires-Dist: cookiecutter (==1.7.3) ; extra == 'modelcreation'
Provides-Extra: natten
Requires-Dist: natten (>=0.14.4) ; extra == 'natten'
Provides-Extra: onnx
Requires-Dist: onnxconverter-common ; extra == 'onnx'
Requires-Dist: tf2onnx ; extra == 'onnx'
Requires-Dist: onnxruntime (>=1.4.0) ; extra == 'onnx'
Requires-Dist: onnxruntime-tools (>=1.4.2) ; extra == 'onnx'
Provides-Extra: onnxruntime
Requires-Dist: onnxruntime (>=1.4.0) ; extra == 'onnxruntime'
Requires-Dist: onnxruntime-tools (>=1.4.2) ; extra == 'onnxruntime'
Provides-Extra: optuna
Requires-Dist: optuna ; extra == 'optuna'
Provides-Extra: quality
Requires-Dist: black (==22.3) ; extra == 'quality'
Requires-Dist: datasets (!=2.5.0) ; extra == 'quality'
Requires-Dist: isort (>=5.5.4) ; extra == 'quality'
Requires-Dist: flake8 (<6.0.0,>=3.8.3) ; extra == 'quality'
Requires-Dist: GitPython (<3.1.19) ; extra == 'quality'
Requires-Dist: hf-doc-builder (>=0.3.0) ; extra == 'quality'
Provides-Extra: ray
Requires-Dist: ray[tune] ; extra == 'ray'
Provides-Extra: retrieval
Requires-Dist: datasets (!=2.5.0) ; extra == 'retrieval'
Provides-Extra: sagemaker
Requires-Dist: sagemaker (>=2.31.0) ; extra == 'sagemaker'
Provides-Extra: sentencepiece
Requires-Dist: sentencepiece (!=0.1.92,>=0.1.91) ; extra == 'sentencepiece'
Requires-Dist: protobuf (<=3.20.2) ; extra == 'sentencepiece'
Provides-Extra: serving
Requires-Dist: pydantic ; extra == 'serving'
Requires-Dist: uvicorn ; extra == 'serving'
Requires-Dist: fastapi ; extra == 'serving'
Requires-Dist: starlette ; extra == 'serving'
Provides-Extra: sigopt
Requires-Dist: sigopt ; extra == 'sigopt'
Provides-Extra: sklearn
Requires-Dist: scikit-learn ; extra == 'sklearn'
Provides-Extra: speech
Requires-Dist: torchaudio ; extra == 'speech'
Requires-Dist: librosa ; extra == 'speech'
Requires-Dist: pyctcdecode (>=0.4.0) ; extra == 'speech'
Requires-Dist: phonemizer ; extra == 'speech'
Requires-Dist: kenlm ; extra == 'speech'
Provides-Extra: testing
Requires-Dist: pytest ; extra == 'testing'
Requires-Dist: pytest-xdist ; extra == 'testing'
Requires-Dist: timeout-decorator ; extra == 'testing'
Requires-Dist: parameterized ; extra == 'testing'
Requires-Dist: psutil ; extra == 'testing'
Requires-Dist: datasets (!=2.5.0) ; extra == 'testing'
Requires-Dist: dill (<0.3.5) ; extra == 'testing'
Requires-Dist: evaluate (>=0.2.0) ; extra == 'testing'
Requires-Dist: pytest-timeout ; extra == 'testing'
Requires-Dist: black (==22.3) ; extra == 'testing'
Requires-Dist: sacrebleu (<2.0.0,>=1.4.12) ; extra == 'testing'
Requires-Dist: rouge-score (!=0.0.7,!=0.0.8,!=0.1,!=0.1.1) ; extra == 'testing'
Requires-Dist: nltk ; extra == 'testing'
Requires-Dist: GitPython (<3.1.19) ; extra == 'testing'
Requires-Dist: hf-doc-builder (>=0.3.0) ; extra == 'testing'
Requires-Dist: protobuf (<=3.20.2) ; extra == 'testing'
Requires-Dist: sacremoses ; extra == 'testing'
Requires-Dist: rjieba ; extra == 'testing'
Requires-Dist: safetensors (>=0.2.1) ; extra == 'testing'
Requires-Dist: beautifulsoup4 ; extra == 'testing'
Requires-Dist: cookiecutter (==1.7.3) ; extra == 'testing'
Provides-Extra: tf
Requires-Dist: tensorflow (<2.12,>=2.4) ; extra == 'tf'
Requires-Dist: onnxconverter-common ; extra == 'tf'
Requires-Dist: tf2onnx ; extra == 'tf'
Requires-Dist: tensorflow-text ; extra == 'tf'
Requires-Dist: keras-nlp (>=0.3.1) ; extra == 'tf'
Provides-Extra: tf-cpu
Requires-Dist: tensorflow-cpu (<2.12,>=2.4) ; extra == 'tf-cpu'
Requires-Dist: onnxconverter-common ; extra == 'tf-cpu'
Requires-Dist: tf2onnx ; extra == 'tf-cpu'
Requires-Dist: tensorflow-text ; extra == 'tf-cpu'
Requires-Dist: keras-nlp (>=0.3.1) ; extra == 'tf-cpu'
Provides-Extra: tf-speech
Requires-Dist: librosa ; extra == 'tf-speech'
Requires-Dist: pyctcdecode (>=0.4.0) ; extra == 'tf-speech'
Requires-Dist: phonemizer ; extra == 'tf-speech'
Requires-Dist: kenlm ; extra == 'tf-speech'
Provides-Extra: timm
Requires-Dist: timm ; extra == 'timm'
Provides-Extra: tokenizers
Requires-Dist: tokenizers (!=0.11.3,<0.14,>=0.11.1) ; extra == 'tokenizers'
Provides-Extra: torch
Requires-Dist: torch (>=1.12.1) ; extra == 'torch'
Provides-Extra: torch-speech
Requires-Dist: torchaudio ; extra == 'torch-speech'
Requires-Dist: librosa ; extra == 'torch-speech'
Requires-Dist: pyctcdecode (>=0.4.0) ; extra == 'torch-speech'
Requires-Dist: phonemizer ; extra == 'torch-speech'
Requires-Dist: kenlm ; extra == 'torch-speech'
Provides-Extra: torchhub
Requires-Dist: filelock ; extra == 'torchhub'
Requires-Dist: huggingface-hub (<0.14.0,>=0.11.0) ; extra == 'torchhub'
Requires-Dist: importlib-metadata ; extra == 'torchhub'
Requires-Dist: numpy (>=1.17) ; extra == 'torchhub'
Requires-Dist: packaging (>=20.0) ; extra == 'torchhub'
Requires-Dist: protobuf (<=3.20.2) ; extra == 'torchhub'
Requires-Dist: regex (!=2019.12.17) ; extra == 'torchhub'
Requires-Dist: requests ; extra == 'torchhub'
Requires-Dist: sentencepiece (!=0.1.92,>=0.1.91) ; extra == 'torchhub'
Requires-Dist: torch (>=1.12.1) ; extra == 'torchhub'
Requires-Dist: tokenizers (!=0.11.3,<0.14,>=0.11.1) ; extra == 'torchhub'
Requires-Dist: tqdm (>=4.27) ; extra == 'torchhub'
Provides-Extra: video
Requires-Dist: decord (==0.6.0) ; extra == 'video'
Provides-Extra: vision
Requires-Dist: Pillow ; extra == 'vision'
